orca_gym/__init__.py
orca_gym/py.typed
orca_gym/adapters/__init__.py
orca_gym/adapters/rllib/__init__.py
orca_gym/adapters/rllib/appo_catalog.py
orca_gym/adapters/rllib/metrics_callback.py
orca_gym/adapters/robomimic/__init__.py
orca_gym/adapters/robomimic/dataset_util.py
orca_gym/adapters/robomimic/robomimic_env.py
orca_gym/adapters/robomimic/task/__init__.py
orca_gym/adapters/robomimic/task/abstract_task.py
orca_gym/adapters/robomimic/task/pick_place_task.py
orca_gym/adapters/robomimic/task/scene_manage.py
orca_gym/adapters/robosuite/__init__.py
orca_gym/adapters/robosuite/macros.py
orca_gym/adapters/robosuite/controllers/__init__.py
orca_gym/adapters/robosuite/controllers/base_controller.py
orca_gym/adapters/robosuite/controllers/controller_config.py
orca_gym/adapters/robosuite/controllers/controller_factory.py
orca_gym/adapters/robosuite/controllers/ik.py
orca_gym/adapters/robosuite/controllers/joint_pos.py
orca_gym/adapters/robosuite/controllers/joint_tor.py
orca_gym/adapters/robosuite/controllers/joint_vel.py
orca_gym/adapters/robosuite/controllers/osc.py
orca_gym/adapters/robosuite/controllers/config/default_baxter.json
orca_gym/adapters/robosuite/controllers/config/default_iiwa.json
orca_gym/adapters/robosuite/controllers/config/default_jaco.json
orca_gym/adapters/robosuite/controllers/config/default_kinova3.json
orca_gym/adapters/robosuite/controllers/config/default_panda.json
orca_gym/adapters/robosuite/controllers/config/default_sawyer.json
orca_gym/adapters/robosuite/controllers/config/default_ur5e.json
orca_gym/adapters/robosuite/controllers/config/ik_pose.json
orca_gym/adapters/robosuite/controllers/config/joint_position.json
orca_gym/adapters/robosuite/controllers/config/joint_torque.json
orca_gym/adapters/robosuite/controllers/config/joint_velocity.json
orca_gym/adapters/robosuite/controllers/config/osc_pose.json
orca_gym/adapters/robosuite/controllers/config/osc_position.json
orca_gym/adapters/robosuite/controllers/interpolators/__init__.py
orca_gym-26.1.8.dist-info/METADATA
orca_gym-26.1.8.dist-info/WHEEL
orca_gym-26.1.8.dist-info/entry_points.txt
orca_gym-26.1.8.dist-info/top_level.txt
orca_gym-26.1.8.dist-info/RECORD
