Metadata-Version: 2.4
Name: orca-gym
Version: 26.1.8
Summary: OrcaGym Core - Cloud-native robotics simulation platform compatible with Gymnasium API
Author-email: 松应科技 <huangwei@orca3d.cn>
License: MIT
Project-URL: Homepage, https://github.com/openverse-orca/OrcaGym
Project-URL: Documentation, https://github.com/openverse-orca/OrcaGym
Project-URL: Repository, https://github.com/openverse-orca/OrcaGym
Project-URL: Bug Tracker, https://github.com/openverse-orca/OrcaGym/issues
Keywords: robotics,simulation,reinforcement-learning,gymnasium,mujoco
Classifier: Development Status :: 4 - Beta
Classifier: Intended Audience :: Science/Research
Classifier: License :: OSI Approved :: MIT License
Classifier: Programming Language :: Python :: 3
Classifier: Programming Language :: Python :: 3.9
Classifier: Programming Language :: Python :: 3.10
Classifier: Programming Language :: Python :: 3.11
Classifier: Programming Language :: Python :: 3.12
Classifier: Topic :: Scientific/Engineering :: Artificial Intelligence
Requires-Python: >=3.9
Requires-Dist: numpy==2.2.6
Requires-Dist: scipy==1.16.2
Requires-Dist: scipy-stubs==1.16.2.4
Requires-Dist: grpcio==1.66.1
Requires-Dist: grpcio-tools==1.66.1
Requires-Dist: gymnasium==1.2.1
Requires-Dist: mujoco==3.3.3
Requires-Dist: aiofiles==25.1.0
Requires-Dist: termcolor>=2.4.0
Provides-Extra: dev
Requires-Dist: pytest; extra == "dev"
Requires-Dist: pytest-cov; extra == "dev"
Requires-Dist: flake8; extra == "dev"
Requires-Dist: black; extra == "dev"
Requires-Dist: mypy; extra == "dev"
Provides-Extra: rl
Requires-Dist: stable-baselines3>=2.3.2; extra == "rl"
Requires-Dist: sb3_contrib>=2.3.0; extra == "rl"
Requires-Dist: tensorboard; extra == "rl"
Provides-Extra: imitation
Requires-Dist: h5py; extra == "imitation"
Requires-Dist: opencv-python; extra == "imitation"
Requires-Dist: tqdm; extra == "imitation"
Provides-Extra: devices
Requires-Dist: pygame>=2.6.0; extra == "devices"
Provides-Extra: sensors
Requires-Dist: websockets; extra == "sensors"
Requires-Dist: av; extra == "sensors"
Requires-Dist: opencv-python; extra == "sensors"
Requires-Dist: matplotlib; extra == "sensors"
Provides-Extra: tools
Requires-Dist: pyyaml; extra == "tools"
Requires-Dist: trimesh; extra == "tools"
Requires-Dist: requests; extra == "tools"
Requires-Dist: tqdm; extra == "tools"
Provides-Extra: robomimic
Requires-Dist: h5py; extra == "robomimic"
Requires-Dist: termcolor; extra == "robomimic"
Requires-Dist: opencv-python; extra == "robomimic"
Provides-Extra: robosuite
Requires-Dist: numba; extra == "robosuite"
Provides-Extra: all
Requires-Dist: stable-baselines3>=2.3.2; extra == "all"
Requires-Dist: sb3_contrib>=2.3.0; extra == "all"
Requires-Dist: tensorboard; extra == "all"
Requires-Dist: h5py; extra == "all"
Requires-Dist: opencv-python; extra == "all"
Requires-Dist: tqdm; extra == "all"
Requires-Dist: pygame>=2.6.0; extra == "all"
Requires-Dist: websockets; extra == "all"
Requires-Dist: av; extra == "all"
Requires-Dist: matplotlib; extra == "all"
Requires-Dist: pyyaml; extra == "all"
Requires-Dist: trimesh; extra == "all"
Requires-Dist: requests; extra == "all"
Requires-Dist: termcolor; extra == "all"
Requires-Dist: numba; extra == "all"
Requires-Dist: flask; extra == "all"
